assemblyinfo/__init__.py
assemblyinfo/interface.py
assemblyinfo/build/build.py
assemblyinfo/build/schema.py
assemblyinfo/core/__init__.py
assemblyinfo/core/acc.py
assemblyinfo/core/assembly.py
assemblyinfo/core/chrom.py
assemblyinfo/core/info.py
assemblyinfo/data/db.parquet
assemblyinfo/data/init_db.tsv
assemblyinfo-0.0.1.dist-info/METADATA
assemblyinfo-0.0.1.dist-info/WHEEL
assemblyinfo-0.0.1.dist-info/licenses/LICENSE
assemblyinfo-0.0.1.dist-info/RECORD
